{
  "cross_alignment_max_delta": 43,
  "cross_alignment_message": "boundary_overlap_exceeds_tolerance",
  "cross_alignment_passed": false,
  "cross_centroid_distance": 0.041447,
  "cross_inconsistency_score": 0.162548,
  "cross_overlap_score": 0.002379,
  "ir_hotspot_area_fraction": 0.24556,
  "ir_hotspot_compactness": 0.269657,
  "ir_max_gradient": 0.738756,
  "ir_mean_hotspot_intensity": 2.994986,
  "pc_max_roughness": 0.597385,
  "pc_mean_curvature": 0.042753,
  "pc_p95_normal_deviation": 0.839399
}